django_natural_sort/__init__.py
django_natural_sort/backend.py
django_natural_sort/filters.py
django_natural_sort/helper.py
django_natural_sort/ordering.py
django_natural_sort/tests/__init__.py
django_natural_sort/tests/factories.py
django_natural_sort/tests/test_filter.py
django_natural_sort/tests/test_helper.py
sampleapp/__init__.py
sampleapp/admin.py
sampleapp/apps.py
sampleapp/models.py
sampleapp/tests.py
sampleapp/views.py
sampleapp/migrations/0001_initial.py
sampleapp/migrations/__init__.py
django_natural_sort-0.1.1.dist-info/LICENSE
django_natural_sort-0.1.1.dist-info/METADATA
django_natural_sort-0.1.1.dist-info/WHEEL
django_natural_sort-0.1.1.dist-info/top_level.txt
django_natural_sort-0.1.1.dist-info/RECORD
