Metadata-Version: 2.1
Name: django-natural-sort
Version: 0.1.1
Summary: Natural sorting for Django and Django REST Framework
Home-page: https://github.com/akindele214/django-natural-sort
Author: Lekan Akindele
Author-email: lekan.akindele12@gmail.com
Project-URL: Bug Tracker, https://github.com/akindele214/django-natural-sort/issues
Project-URL: Documentation, https://github.com/akindele214/django-natural-sort
Project-URL: Source Code, https://github.com/akindele214/django-natural-sort
Keywords: django,drf,natural sort,sorting,ordering
Classifier: Development Status :: 4 - Beta
Classifier: Intended Audience :: Developers
Classifier: License :: OSI Approved :: MIT License
Classifier: Programming Language :: Python :: 3.6
Classifier: Programming Language :: Python :: 3.7
Classifier: Programming Language :: Python :: 3.8
Classifier: Programming Language :: Python :: 3.9
Classifier: Programming Language :: Python :: 3.10
Classifier: Framework :: Django
Classifier: Framework :: Django :: 3.2
Classifier: Framework :: Django :: 4.0
Classifier: Framework :: Django :: 4.1
Classifier: Framework :: Django :: 4.2
Requires-Python: >=3.6
License-File: LICENSE
Requires-Dist: Django >=3.2
Requires-Dist: djangorestframework >=3.9.0
